hatch_deps_selector/__about__.py
hatch_deps_selector/__init__.py
hatch_deps_selector/hooks.py
hatch_deps_selector/plugin.py
hatch_deps_selector-0.1.2.dist-info/METADATA
hatch_deps_selector-0.1.2.dist-info/WHEEL
hatch_deps_selector-0.1.2.dist-info/entry_points.txt
hatch_deps_selector-0.1.2.dist-info/licenses/LICENSE
hatch_deps_selector-0.1.2.dist-info/licenses/LICENSE.txt
hatch_deps_selector-0.1.2.dist-info/RECORD
