Metadata-Version: 2.3
Name: hatch-deps-selector
Version: 0.1.2
Summary: Select variants of your dependencies with environment variables
Project-URL: Documentation, https://github.com/jupyter-book/hatch-deps-selector#readme
Project-URL: Issues, https://github.com/jupyter-book/hatch-deps-selector/issues
Project-URL: Source, https://github.com/jupyter-book/hatch-deps-selector
Author-email: Angus Hollands <goosey15@gmail.com>
License: The MIT License (MIT)
License-File: LICENSE
License-File: LICENSE.txt
Classifier: Development Status :: 4 - Beta
Classifier: Programming Language :: Python
Classifier: Programming Language :: Python :: 3.8
Classifier: Programming Language :: Python :: 3.9
Classifier: Programming Language :: Python :: 3.10
Classifier: Programming Language :: Python :: 3.11
Classifier: Programming Language :: Python :: 3.12
Classifier: Programming Language :: Python :: Implementation :: CPython
Classifier: Programming Language :: Python :: Implementation :: PyPy
Requires-Python: >=3.8
